nipy-0.6.1.dist-info/LICENSE
nipy-0.6.1.dist-info/METADATA
nipy-0.6.1.dist-info/entry_points.txt
nipy-0.6.1.dist-info/RECORD
nipy-0.6.1.dist-info/WHEEL
nipy/pkg_info.py
nipy/info.py
nipy/conftest.py
nipy/__init__.py
nipy/io/nifti_ref.py
nipy/io/files.py
nipy/io/api.py
nipy/io/nibcompat.py
nipy/io/__init__.py
nipy/io/tests/test_image_io.py
nipy/io/tests/test_nifti_ref.py
nipy/io/tests/test_save.py
nipy/io/tests/test_nibcompat.py
nipy/io/tests/__init__.py
nipy/io/imageformats/__init__.py
nipy/cli/diagnose.py
nipy/cli/tsdiffana.py
nipy/cli/__init__.py
nipy/cli/realign4d.py
nipy/cli/img4dto3d.py
nipy/cli/img3dto4d.py
nipy/tests/scriptrunner.py
nipy/tests/test_scripts.py
nipy/tests/__init__.py
nipy/algorithms/kernel_smooth.py
nipy/algorithms/interpolation.py
nipy/algorithms/resample.py
nipy/algorithms/optimize.py
nipy/algorithms/fwhm.py
nipy/algorithms/__init__.py
nipy/algorithms/segmentation/segmentation.py
nipy/algorithms/segmentation/_segmentation.cpython-311-x86_64-linux-gnu.so
nipy/algorithms/segmentation/brain_segmentation.py
nipy/algorithms/segmentation/__init__.py
nipy/algorithms/segmentation/tests/__init__.py
nipy/algorithms/segmentation/tests/test_segmentation.py
nipy/algorithms/registration/chain_transform.py
nipy/algorithms/registration/affine.py
nipy/algorithms/registration/type_check.py
nipy/algorithms/registration/resample.py
nipy/algorithms/registration/histogram_registration.py
nipy/algorithms/registration/_registration.cpython-311-x86_64-linux-gnu.so
nipy/algorithms/registration/optimizer.py
nipy/algorithms/registration/similarity_measures.py
nipy/algorithms/registration/transform.py
nipy/algorithms/registration/scripting.py
nipy/algorithms/registration/__init__.py
nipy/algorithms/registration/polyaffine.py
nipy/algorithms/registration/groupwise_registration.py
nipy/algorithms/registration/tests/test_polyaffine.py
nipy/algorithms/registration/tests/test_slice_timing.py
nipy/algorithms/registration/tests/test_fmri_realign4d.py
nipy/algorithms/registration/tests/test_chain_transforms.py
nipy/algorithms/registration/tests/test_scripting.py
