Metadata-Version: 2.1
Name: nipy
Version: 0.6.1
Summary: A python package for analysis of neuroimaging data
Maintainer-Email: nipy developers <neuroimaging@python.org>
License: Copyright (c) 2006-2024, NIPY Developers
Classifier: Development Status :: 3 - Alpha
Classifier: Environment :: Console
Classifier: Intended Audience :: Science/Research
Classifier: License :: OSI Approved :: BSD License
Classifier: Operating System :: OS Independent
Classifier: Programming Language :: Python :: 3.8
Classifier: Programming Language :: Python :: 3.9
Classifier: Programming Language :: Python :: 3.10
Classifier: Programming Language :: Python :: 3.11
Classifier: Programming Language :: Python :: 3.12
Classifier: Programming Language :: Python :: 3.13
Classifier: Topic :: Scientific/Engineering
Project-URL: Homepage, https://nipy.org/nipy
Project-URL: Documentation, http://nipy.org/nipy/documentation.html
Project-URL: Source, https://github.com/nipy/nipy
Project-URL: Download, https://pypi.org/project/nipy/#files
Project-URL: Tracker, https://github.com/nipy/nipy/issues
Requires-Python: >=3.8
Requires-Dist: numpy>=1.22
Requires-Dist: scipy>=1.8
Requires-Dist: nibabel>=3.2
Requires-Dist: sympy>=1.9
Requires-Dist: transforms3d
Requires-Dist: pre-commit; extra == "developer"
Requires-Dist: rtoml; extra == "developer"
Requires-Dist: sphinx>=7.0; extra == "docs"
Requires-Dist: numpydoc>=1.6.0; extra == "docs"
Requires-Dist: matplotlib; extra == "docs"
Requires-Dist: texext; extra == "docs"
Requires-Dist: ipython; extra == "docs"
Requires-Dist: matplotlib>=3; extra == "optional"
Requires-Dist: matplotlib>=3; extra == "test"
Requires-Dist: pytest>=7.2; extra == "test"
Requires-Dist: pytest-cov>=4.0; extra == "test"
Requires-Dist: pytest-doctestplus; extra == "test"
Provides-Extra: developer
Provides-Extra: docs
Provides-Extra: optional
Provides-Extra: test
